ZabbixQywechat/__init__.py
ZabbixQywechat-1.1.1.dist-info/LICENSE
ZabbixQywechat-1.1.1.dist-info/METADATA
ZabbixQywechat-1.1.1.dist-info/WHEEL
ZabbixQywechat-1.1.1.dist-info/top_level.txt
ZabbixQywechat-1.1.1.dist-info/RECORD
